oscsipm/__init__.py
oscsipm/crosstalk.py
oscsipm/histogram.py
oscsipm/oscillogram.py
oscsipm-0.6.4.dist-info/LICENSE
oscsipm-0.6.4.dist-info/METADATA
oscsipm-0.6.4.dist-info/WHEEL
oscsipm-0.6.4.dist-info/top_level.txt
oscsipm-0.6.4.dist-info/RECORD
