Metadata-Version: 2.1
Name: oscsipm
Version: 0.6.4
Summary: Instruments to make photocounting statistics from histograms and raw oscillograms
Home-page: https://github.com/vongostev/OscSiPM
Author: Pavel Gostev
Author-email: gostev.pavel@physics.msu.ru
License: UNKNOWN
Platform: UNKNOWN
Classifier: Programming Language :: Python :: 3
Classifier: License :: OSI Approved :: MIT License
Classifier: Operating System :: OS Independent
Requires-Python: >=3.6
Requires-Dist: numpy
Requires-Dist: scipy
Requires-Dist: matplotlib
Requires-Dist: lecroyparser
Requires-Dist: joblib
Requires-Dist: dataclasses
Requires-Dist: compress-pickle
Requires-Dist: tekwfm2
Requires-Dist: fpdet
Requires-Dist: pyfftw
Requires-Dist: numba
